chunspell-2.0.4.dist-info/WHEEL
chunspell-2.0.4.dist-info/LICENSE
chunspell-2.0.4.dist-info/top_level.txt
chunspell-2.0.4.dist-info/RECORD
chunspell-2.0.4.dist-info/METADATA
hunspell/hunspell.pypy310-pp73-x86_64-linux-gnu.so
hunspell/__init__.py
hunspell/hunspell.pyx
hunspell/libhunspell-1.7.so.0
hunspell/hunspell.cpp
hunspell/hunspell.pxd
hunspell/_version.py
hunspell/dictionaries/en_US.aff
hunspell/dictionaries/en_US.dic
