Metadata-Version: 2.1
Name: chunspell
Version: 2.0.4
Summary: A wrapper on hunspell for use in Python
Home-page: https://github.com/cdhigh/chunspell
Download-URL: https://github.com/cdhigh/chunspell/tarball/v2.0.4
Author: cdhigh
Author-email: akindleear@gmail.com
License: MIT + MPL 1.1/GPL 2.0/LGPL 2.1
Keywords: hunspell,spelling,correction
Classifier: Development Status :: 5 - Production/Stable
Classifier: Topic :: Utilities
Classifier: License :: OSI Approved :: MIT License
Classifier: Natural Language :: English
Classifier: Programming Language :: Python :: 3
License-File: LICENSE
